Workbook
Name GrowthRate: Assumptions!$B$12
Name TaxRate: Assumptions!$B$13
Name AvgCheck: Assumptions!$B$4

Sheet Assumptions
A1: Model Assumptions
A3: Parameter | B3: Value | C3: Unit
A4: Average Check Size | B4: 42.5 | C4: USD
A5: Covers Per Day - Weekday | B5: 85 | C5: covers
A6: Covers Per Day - Weekend | B6: 140 | C6: covers
A7: Food Cost % | B7: 0.32 | C7: %
A8: Beverage Cost % | B8: 0.22 | C8: %
A9: Labor Cost % | B9: 0.28 | C9: %
A10: Monthly Rent | B10: 8500 | C10: USD
A11: Annual Growth Rate | B11: 0.05 | C11: %
A12: Tax Rate | B12: 0.21 | C12: %
A13: Tip Rate | B13: 0.18 | C13: %
A14: Weekend Days Per Month | B14: 8 | C14: days
A15: Weekday Days Per Month | B15: 22 | C15: days

Sheet Revenue Build
A1: Monthly Revenue Build
A3: Metric | B3: 45658 | C3: 45689 | D3: 45717 | E3: 45748 | F3: 45778 | G3: 45809 | H3: 45839 | I3: 45870 | J3: 45901 | K3: 45931 | L3: 45962 | M3: 45992
A4: Weekday Covers | B4: =Assumptions!B6*Assumptions!B15 | C4: =Assumptions!B6*Assumptions!B15 | D4: =Assumptions!B6*Assumptions!B15 | E4: =Assumptions!B6*Assumptions!B15 | F4: =Assumptions!B6*Assumptions!B15 | G4: =Assumptions!B6*Assumptions!B15 | H4: =Assumptions!B6*Assumptions!B15 | I4: =Assumptions!B6*Assumptions!B15 | J4: =Assumptions!B6*Assumptions!B15 | K4: =Assumptions!B6*Assumptions!B15 | L4: =Assumptions!B6*Assumptions!B15 | M4: =Assumptions!B6*Assumptions!B15
A5: Weekend Covers | B5: =Assumptions!B7*Assumptions!B14 | C5: =Assumptions!B7*Assumptions!B14 | D5: =Assumptions!B7*Assumptions!B14 | E5: =Assumptions!B7*Assumptions!B14 | F5: =Assumptions!B7*Assumptions!B14 | G5: =Assumptions!B7*Assumptions!B14 | H5: =Assumptions!B7*Assumptions!B14 | I5: =Assumptions!B7*Assumptions!B14 | J5: =Assumptions!B7*Assumptions!B14 | K5: =Assumptions!B7*Assumptions!B14 | L5: =Assumptions!B7*Assumptions!B14 | M5: =Assumptions!B7*Assumptions!B14
A6: Total Covers | B6: =B4+B5 | C6: =C4+C5 | D6: =D4+D5 | E6: =E4+E5 | F6: =F4+F5 | G6: =G4+G5 | H6: =H4+H5 | I6: =I4+I5 | ... M6: =M4+M5
A8: Gross Revenue | B8: =B6*Assumptions!B4 | C8: =C6*Assumptions!B4 | D8: =D6*Assumptions!B4 | E8: =E6*Assumptions!B4 | F8: =F6*Assumptions!B4 | G8: =G6*Assumptions!B4 | H8: =H6*Assumptions!B4 | I8: =I6*Assumptions!B4 | J8: =J6*Assumptions!B4 | K8: =K6*Assumptions!B4 | L8: =L6*Assumptions!B4 | M8: =M6*Assumptions!B4
A9: Food Revenue | B9: =B8*0.6 | C9: =C8*0.6 | D9: =D8*0.6 | E9: =E8*0.6 | F9: =F8*0.6 | G9: =G8*0.6 | H9: =H8*0.6 | I9: =I8*0.6 | ... M9: =M8*0.6
A10: Beverage Revenue | B10: =B8*0.4 | C10: =C8*0.4 | D10: =D8*0.4 | E10: =E8*0.4 | F10: =F8*0.4 | G10: =G8*0.4 | H10: =H8*0.4 | I10: =I8*0.4 | ... M10: =M8*0.4

Sheet P&L
A1: Profit & Loss Statement
A3: Line Item | B3: 45658 | C3: 45689 | D3: 45717 | E3: 45748 | F3: 45778 | G3: 45809 | H3: 45839 | I3: 45870 | J3: 45901 | K3: 45931 | L3: 45962 | M3: 45992
A4: Gross Revenue | B4: ='Revenue Build'!B8 | C4: ='Revenue Build'!C8 | D4: ='Revenue Build'!D8 | E4: ='Revenue Build'!E8 | F4: ='Revenue Build'!F8 | G4: ='Revenue Build'!G8 | H4: ='Revenue Build'!H8 | I4: ='Revenue Build'!I8 | ... M4: ='Revenue Build'!M8
A5: Food Revenue | B5: ='Revenue Build'!B9 | C5: ='Revenue Build'!C9 | D5: ='Revenue Build'!D9 | E5: ='Revenue Build'!E9 | F5: ='Revenue Build'!F9 | G5: ='Revenue Build'!G9 | H5: ='Revenue Build'!H9 | I5: ='Revenue Build'!I9 | ... M5: ='Revenue Build'!M9
A6: Beverage Revenue | B6: ='Revenue Build'!B10 | C6: ='Revenue Build'!C10 | D6: ='Revenue Build'!D10 | E6: ='Revenue Build'!E10 | F6: ='Revenue Build'!F10 | G6: ='Revenue Build'!G10 | H6: ='Revenue Build'!H10 | I6: ='Revenue Build'!I10 | ... M6: ='Revenue Build'!M10
A8: Cost of Goods Sold
A9: Food COGS | B9: =B5*Assumptions!B8 | C9: =C5*Assumptions!B8 | D9: =D5*Assumptions!B8 | E9: =E5*Assumptions!B8 | F9: =F5*Assumptions!B8 | G9: =G5*Assumptions!B8 | H9: =H5*Assumptions!B8 | I9: =I5*Assumptions!B8 | J9: =J5*Assumptions!B8 | K9: =K5*Assumptions!B8 | L9: =L5*Assumptions!B8 | M9: =M5*Assumptions!B8
A10: Beverage COGS | B10: =B6*Assumptions!B9 | C10: =C6*Assumptions!B9 | D10: =D6*Assumptions!B9 | E10: =E6*Assumptions!B9 | F10: =F6*Assumptions!B9 | G10: =G6*Assumptions!B9 | H10: =H6*Assumptions!B9 | I10: =I6*Assumptions!B9 | J10: =J6*Assumptions!B9 | K10: =K6*Assumptions!B9 | L10: =L6*Assumptions!B9 | M10: =M6*Assumptions!B9
A11: Total COGS | B11: =B9+B10 | C11: =C9+C10 | D11: =D9+D10 | E11: =E9+E10 | F11: =F9+F10 | G11: =G9+G10 | H11: =H9+H10 | I11: =I9+I10 | ... M11: =M9+M10
A13: Gross Profit | B13: =B4-B11 | C13: =C4-C11 | D13: =D4-D11 | E13: =E4-E11 | F13: =F4-F11 | G13: =G4-G11 | H13: =H4-H11 | I13: =I4-I11 | ... M13: =M4-M11
A14: Gross Margin % | B14: =B13/B4 | C14: =C13/C4 | D14: =D13/D4 | E14: =E13/E4 | F14: =F13/F4 | G14: =G13/G4 | H14: =H13/H4 | I14: =I13/I4 | ... M14: =M13/M4
A16: Operating Expenses
A17: Labor | B17: =B4*Assumptions!B10 | C17: =C4*Assumptions!B10 | D17: =D4*Assumptions!B10 | E17: =E4*Assumptions!B10 | F17: =F4*Assumptions!B10 | G17: =G4*Assumptions!B10 | H17: =H4*Assumptions!B10 | I17: =I4*Assumptions!B10 | J17: =J4*Assumptions!B10 | K17: =K4*Assumptions!B10 | L17: =L4*Assumptions!B10 | M17: =M4*Assumptions!B10
A18: Rent | B18: =Assumptions!B11 | C18: =Assumptions!B11 | D18: =Assumptions!B11 | E18: =Assumptions!B11 | F18: =Assumptions!B11 | G18: =Assumptions!B11 | H18: =Assumptions!B11 | I18: =Assumptions!B11 | J18: =Assumptions!B11 | K18: =Assumptions!B11 | L18: =Assumptions!B11 | M18: =Assumptions!B11
A19: Utilities | B19: 1549.57 | C19: 2973.13 | D19: 2164.37 | E19: 3361.63 | F19: 3104.47 | G19: 3228.13 | H19: 3121.5 | I19: 2033.61 | J19: 3074.75 | K19: 1716.19 | L19: 3244.33 | M19: 3217.19
A20: Marketing | B20: 1178.14 | C20: 2188.2 | D20: 1582.52 | E20: 1318.82 | F20: 2152.09 | G20: 1186.91 | H20: 840.23 | I20: 1128.32 | J20: 1358.05 | K20: 2269.4 | L20: 2443.71 | M20: 1274.51
A21: Other OpEx | B21: 877.33 | C21: 659.71 | D21: 1183.03 | E21: 782.59 | F21: 1145.31 | G21: 403.81 | H21: =G21*1.1 | I21: 460.71 | J21: 1166.28 | K21: 538.92 | L21: 397.56 | M21: 691.11
A22: Total Operating Expenses | B22: =SUM(B17:B21) | C22: =SUM(C17:C21) | D22: =SUM(D17:D21) | E22: =SUM(E17:E21) | F22: =SUM(F17:F21) | G22: =SUM(G17:G21) | H22: =SUM(H17:H21) | I22: =SUM(I17:I21) | ... M22: =SUM(M17:M21)
A24: Operating Income | B24: =B13-B22 | C24: =C13-C22 | D24: =D13-D22 | E24: =E13-E22 | F24: =F13-F22 | G24: =G13-G22 | H24: =H13-H22 | I24: =I13-I22 | ... M24: =M13-M22
A25: Tax | B25: =B23*Assumptions!B12 | C25: =C23*Assumptions!B12 | D25: =D23*Assumptions!B12 | E25: =E23*Assumptions!B12 | F25: =F23*Assumptions!B12 | G25: =G23*Assumptions!B12 | H25: =H23*Assumptions!B12 | I25: =I23*Assumptions!B12 | J25: =J23*Assumptions!B12 | K25: =K23*Assumptions!B12 | L25: =L23*Assumptions!B12 | M25: =M23*Assumptions!B12
A27: Net Income | B27: =B23-B24 | C27: =C23-C24 | D27: =D23-D24 | E27: =E23-E24 | F27: =F23-F24 | G27: =G23-G24 | H27: =H23-H24 | I27: =I23-I24 | ... M27: =M23-M24

Sheet Balance Sheet
A1: Balance Sheet
B3: 45658 | C3: 45689 | D3: 45717 | E3: 45748 | F3: 45778 | G3: 45809 | H3: 45839 | I3: 45870 | J3: 45901 | K3: 45931 | L3: 45962 | M3: 45992
A4: Total Assets | B4: 222854.51 | C4: 181367.73 | D4: 210620.89 | E4: 201142.31 | F4: 188519.54 | G4: 207658.8 | H4: 175472.25 | I4: 220878.53 | J4: 150169.13 | K4: 242557.52 | L4: 203845.2 | M4: 221943
A5: Total Liabilities | B5: 135757.01 | C5: 97836.3 | D5: 142409.82 | E5: 147643.62 | F5: 105307.66 | G5: 141148.8 | H5: 109776.47 | I5: 128477.77 | J5: 64181.42 | K5: 177541.41 | L5: 138380.97 | M5: 151523.35
A6: Total Equity | B6: 87097.5 | C6: 83531.43 | D6: 68211.07 | E6: 53498.69 | F6: 83211.88 | G6: 66510 | H6: 65695.78 | I6: 92400.76 | J6: 85987.71 | K6: 65016.11 | L6: 65464.23 | M6: 70419.65
